README.md
setup.cfg
setup.py
stock_position_calc/__init__.py
stock_position_calc/app.py
stock_position_calc/currency_formatter.py
stock_position_calc/state.py
stock_position_calc/validate.py
stock_position_calc.egg-info/PKG-INFO
stock_position_calc.egg-info/SOURCES.txt
stock_position_calc.egg-info/dependency_links.txt
stock_position_calc.egg-info/entry_points.txt
stock_position_calc.egg-info/top_level.txt
stock_position_calc/test/__init__.py
stock_position_calc/test/test_app.py