Metadata-Version: 2.1
Name: stock-position-calc
Version: 1.0.11
Summary: A simple program to calculate the right amount of shares to buy while limiting risk.
Home-page: https://github.com/zaironjacobs/stock-position-calc
Author: Zairon Jacobs
Author-email: zaironjacobs@gmail.com
License: MIT
Download-URL: https://github.com/zaironjacobs/stock-position-calc/archive/v1.0.11.tar.gz
Keywords: stock,market,price,calculation,investment,tool
Platform: UNKNOWN
Classifier: Development Status :: 5 - Production/Stable
Classifier: Intended Audience :: End Users/Desktop
Classifier: License :: OSI Approved :: MIT License
Classifier: Operating System :: OS Independent
Classifier: Programming Language :: Python :: 3.8
Classifier: Natural Language :: English
Requires-Python: >=3
